README.rst
setup.cfg
setup.py
deliverybot_extensions/__init__.py
deliverybot_extensions/flask/__init__.py
deliverybot_extensions/flask/meta.py
deliverybot_libs/__init__.py
deliverybot_libs/logging.py
deliverybot_utils.egg-info/PKG-INFO
deliverybot_utils.egg-info/SOURCES.txt
deliverybot_utils.egg-info/dependency_links.txt
deliverybot_utils.egg-info/top_level.txt