Metadata-Version: 1.1
Name: deliverybot-utils
Version: 0.35.0
Summary: A handful set of functionalities shared across all services, written in Python
Home-page: https://github.com/deliverybot/utils
Author: Gabriel Lima
Author-email: gvclima@gmail.com
License: MIT
Platform: UNKNOWN
Classifier: Development Status :: 3 - Alpha
Classifier: Intended Audience :: Developers
Classifier: License :: OSI Approved :: MIT License
Classifier: Operating System :: OS Independent
Classifier: Programming Language :: Python
Classifier: Programming Language :: Python :: 3
Classifier: Topic :: Software Development :: Libraries :: Python Modules
